MANIFEST.in
setup.py
bin/prioritize
nose_priority/__init__.py
nose_priority/data.json
nose_priority.egg-info/PKG-INFO
nose_priority.egg-info/SOURCES.txt
nose_priority.egg-info/dependency_links.txt
nose_priority.egg-info/not-zip-safe
nose_priority.egg-info/requires.txt
nose_priority.egg-info/top_level.txt