Metadata-Version: 1.0
Name: nose-priority
Version: 0.1
Summary: Prioritize nose tests based on past failures
Home-page: https://github.com/criles25/nose_priority
Author: Charles Riley
Author-email: criles25@gmail.com
License: GNU
Platform: UNKNOWN
